<Properties StartupConfiguration="{FF44D884-001A-4F5D-800F-A4803CDBD1D1}|https">
  <MonoDevelop.Ide.DebuggingService.PinnedWatches />
  <MultiItemStartupConfigurations />
  <MonoDevelop.Ide.DebuggingService.Breakpoints>
    <BreakpointStore />
  </MonoDevelop.Ide.DebuggingService.Breakpoints>
  <MonoDevelop.Ide.Workbench ActiveDocument="Test_API/Data/ApplicationDbContext.cs">
    <Files>
      <File FileName="Test_API/Controllers/VillaNumberAPIController.cs" Line="99" Column="8" />
      <File FileName="Test_API/Models/Dto/VillaNumberCreateDTO.cs" />
      <File FileName="Test_API/Models/VillaNumber.cs" />
      <File FileName="Test_API/Models/Dto/VillaNumberDTO.cs" />
      <File FileName="Test_API/Models/Dto/VillaNumberUpdateDTO.cs" />
      <File FileName="Test_API/Data/ApplicationDbContext.cs" Line="32" Column="20" />
      <File FileName="Test_API/Repository/IRepository/IVillaNumberRepository.cs" />
      <File FileName="Test_API/Repository/VillaNumberRepository.cs" />
      <File FileName="Test_API/Repository/IRepository/IRepository.cs" />
      <File FileName="Test_API/Repository/Repository.cs" />
      <File FileName="Test_API/Controllers/VillaAPIController.cs" />
    </Files>
    <Pads>
      <Pad Id="ProjectPad">
        <State name="__root__">
          <Node name="TestAPI" expanded="True">
            <Node name="Test_API" expanded="True">
              <Node name="Controllers" expanded="True" />
              <Node name="Data" expanded="True">
                <Node name="ApplicationDbContext.cs" selected="True" />
              </Node>
              <Node name="Migrations" expanded="True" />
              <Node name="Models" expanded="True">
                <Node name="Dto" expanded="True" />
              </Node>
              <Node name="Properties" expanded="True" />
              <Node name="Repository" expanded="True">
                <Node name="IRepository" expanded="True" />
              </Node>
            </Node>
          </Node>
        </State>
      </Pad>
    </Pads>
  </MonoDevelop.Ide.Workbench>
  <MonoDevelop.Ide.ItemProperties.Test__API PreferredExecutionTarget="/Applications/Opera.app" />
  <MonoDevelop.Ide.Workspace ActiveConfiguration="Debug" />
</Properties>